ojs_updater/__init__.py
ojs_updater/commons.py
ojs_updater/ojs_update.py
ojs_updater/ojsinstance.py
ojs_updater/settings.py
ojs_updater/updater.py
ojs_updater-0.1.2.dist-info/licenses/LICENSE
tests/__init__.py
tests/conftest.py
tests/test_commons.py
tests/test_ojsinstance.py
tests/test_update.py
tests/test_updater.py
ojs_updater-0.1.2.dist-info/METADATA
ojs_updater-0.1.2.dist-info/WHEEL
ojs_updater-0.1.2.dist-info/entry_points.txt
ojs_updater-0.1.2.dist-info/top_level.txt
ojs_updater-0.1.2.dist-info/RECORD
