Metadata-Version: 2.4
Name: ojs_updater
Version: 0.1.2
Summary: Simple script to update multiple ojs instances on the same system.
Author-email: "UB Frankfurt a. M." <ublabs@ub.uni-frankfurt.de>
License: MPL 2.0
Project-URL: Homepage, https://github.com/ubffm/ojs_updater
Platform: linux
Classifier: Development Status :: 4 - Beta
Classifier: Environment :: Console
Classifier: License :: OSI Approved :: Mozilla Public License 2.0 (MPL 2.0)
Classifier: Operating System :: POSIX :: Linux
Requires-Python: >=3.6
License-File: LICENSE
Requires-Dist: packaging==21.0
Requires-Dist: PyYAML==6.0.1
Requires-Dist: zc.lockfile==2.0
Requires-Dist: schema==0.7.4
Dynamic: license-file
